caller69-0.1.0.dist-info/licenses/LICENSE
webhook_package/__init__.py
caller69-0.1.0.dist-info/METADATA
caller69-0.1.0.dist-info/WHEEL
caller69-0.1.0.dist-info/top_level.txt
caller69-0.1.0.dist-info/RECORD
