Metadata-Version: 2.4
Name: caller69
Version: 0.1.0
Summary: A Python package that triggers a webhook on install
Home-page: https://github.com/yourusername/webhook-package
Author: Your Name
Author-email: Your Name <your.email@example.com>
License-Expression: MIT
Classifier: Programming Language :: Python :: 3
Classifier: Operating System :: OS Independent
Requires-Python: >=3.6
License-File: LICENSE
Dynamic: author
Dynamic: home-page
Dynamic: license-file
Dynamic: requires-python
